{
    "DataModelDetail": [
        {
            "attributes": [
                {
                    "logicalName": "As Of Date",
                    "isPk": "NO",
                    "isNull": "NO",
                    "ldd": "Date",
                    "gcd": "Refers to the date as on which the snapshot of source data extracted for processing.",
                    "isPII": "NO"
                },
                {
                    "logicalName": "As Of Date",
                    "isPk": "YES",
                    "isNull": "NO",
                    "ldd": "Date",
                    "gcd": "Refers to the date as on which the snapshot of source data extracted for processing.",
                    "isPII": "NO"
                },
                {
                    "logicalName": "Consent Purpose Category",
                    "isPk": "NO",
                    "isNull": "YES",
                    "ldd": "Code_Alphanumeric",
                    "gcd": "Refers to the LOV for Consent Category.",
                    "isPII": "NO"
                },
                {
                    "logicalName": "Consent Purpose Category",
                    "isPk": "YES",
                    "isNull": "NO",
                    "ldd": "Code_Alphanumeric",
                    "gcd": "Refers to the LOV for Consent Category.",
                    "isPII": "NO"
                },
                {
                    "logicalName": "Consent Purpose Code",
                    "isPk": "NO",
                    "isNull": "NO",
                    "ldd": "Code_Alphanumeric",
                    "gcd": "Refers to the code generated by Source System associated with the Consent Purpose.",
                    "isPII": "NO"
                },
                {
                    "logicalName": "Consent Purpose Code",
                    "isPk": "YES",
                    "isNull": "NO",
                    "ldd": "Code_Alphanumeric",
                    "gcd": "Refers to the code generated by Source System associated with the Consent Purpose.",
                    "isPII": "NO"
                },
                {
                    "logicalName": "Consent Purpose Description",
                    "isPk": "NO",
                    "isNull": "YES",
                    "ldd": "Description_Medium",
                    "gcd": "Refers to the consent text as displayed to the Party in the Source System while collecting Consent.",
                    "isPII": "NO"
                },
                {
                    "logicalName": "Consent Purpose Description",
                    "isPk": "YES",
                    "isNull": "NO",
                    "ldd": "Description_Medium",
                    "gcd": "Refers to the consent text as displayed to the Party in the Source System while collecting Consent.",
                    "isPII": "NO"
                },
                {
                    "logicalName": "Consent Purpose Numeric Identifier",
                    "isPk": "NO",
                    "isNull": "NO",
                    "ldd": "SurrogateKey_Long",
                    "gcd": "Refers to the equivalent numeric identifier of the consent purpose.",
                    "isPII": "NO"
                },
                {
                    "logicalName": "Data Source Code",
                    "isPk": "NO",
                    "isNull": "YES",
                    "ldd": "Code_Alphanumeric",
                    "gcd": "Refers to the source system from where data is extracted. Data can be sourced from multiple sources, this column will Refers to the source code from where the data is extracted for this extraction date.",
                    "isPII": "NO"
                },
                {
                    "logicalName": "Data Source Code",
                    "isPk": "YES",
                    "isNull": "NO",
                    "ldd": "Code_Alphanumeric",
                    "gcd": "Refers to the source system from where data is extracted. Data can be sourced from multiple sources, this column will Refers to the source code from where the data is extracted for this extraction date.",
                    "isPII": "NO"
                },
                {
                    "logicalName": "Dimension Value Closed Flag",
                    "isPk": "NO",
                    "isNull": "YES",
                    "ldd": "Flag",
                    "gcd": "Flag indicates whether the given dimension value record has been disabled or expired. The list of values includes Y- Indicates that the dimension value has been disabled, N- Indicates that the dimension value is not disabled and is still active.",
                    "isPII": "NO"
                },
                {
                    "logicalName": "Record Creation Date",
                    "isPk": "NO",
                    "isNull": "YES",
                    "ldd": "Date",
                    "gcd": "Refers to the record creation date. It has been added to all catalog entities to enable partitioning and archival.",
                    "isPII": "NO"
                },
                {
                    "logicalName": "Seeded Record Flag",
                    "isPk": "NO",
                    "isNull": "YES",
                    "ldd": "Flag",
                    "gcd": "It Indicates if dimension record is seeded by product or not. The SCD component would not overwrite the record if it is set to 'Y'.",
                    "isPII": "NO"
                }
            ],
            "processInfo": [
                {
                    "scdCode": "25",
                    "srcLogicalName": "Stage Consent Purpose Master",
                    "scdName": "scd_25_DIM_CONSENT_PURPOSE_STG_CONSENT_PURPOSE_MASTER",
                    "scdDesc": "Data movement from consent purpose master source to consent purpose dimension",
                    "createdDate": "2024-10-26 06:02:44.0",
                    "modifiedDate": "2024-10-30 08:59:52.0",
                    "isRegistered": "Y"
                }
            ],
            "governance": [
                {
                    "dqId": "DQCUS42595",
                    "btLogicalName": "Consent Purpose Numeric Identifier",
                    "dqDesc": "Consent Purpose Numeric Identifier  should not have duplicates for existing Code",
                    "dqType": "Custom Check",
                    "isCustom": "Seeded",
                    "status": "S",
                    "createdDate": "2024-10-26 04:46:13.0",
                    "modifiedDate": "2024-11-04 04:39:07.0"
                },
                {
                    "dqId": "DQCUS42596",
                    "btLogicalName": "Consent Purpose Numeric Identifier",
                    "dqDesc": "Consent Purpose Numeric Identifier should not change for existing Code",
                    "dqType": "Custom Check",
                    "isCustom": "Seeded",
                    "status": "S",
                    "createdDate": "2024-10-26 04:46:13.0",
                    "modifiedDate": "2024-11-04 04:39:07.0"
                },
                {
                    "dqId": "DQLOV32712",
                    "btLogicalName": "Dimension Value Closed Flag",
                    "dqDesc": "Should have list of values as N,Y",
                    "dqType": "List of Values or Code Check",
                    "isCustom": "Seeded",
                    "status": "S",
                    "createdDate": "2024-10-26 04:46:13.0",
                    "modifiedDate": "2024-11-04 04:39:07.0"
                },
                {
                    "dqId": "DQNMDUP42090",
                    "btLogicalName": "Consent Purpose Numeric Identifier",
                    "dqDesc": "Consent Purpose Numeric Identifier should not have duplicates",
                    "dqType": "Generic Check",
                    "isCustom": "Seeded",
                    "status": "S",
                    "createdDate": "2024-10-26 04:46:13.0",
                    "modifiedDate": "2024-11-04 04:39:07.0"
                },
                {
                    "dqId": "DQSPLCH43002",
                    "btLogicalName": "Data Source Code",
                    "dqDesc": "Data Source Code should only have list of allowed characters",
                    "dqType": "Custom Check",
                    "isCustom": "Seeded",
                    "status": "S",
                    "createdDate": "2024-10-26 04:46:13.0",
                    "modifiedDate": "2024-11-04 04:39:07.0"
                }
            ],
            "useCases": []
        }
    ]
}