[
    {
        "Seniority Code": "vtK9ovy",
        "Standard Seniority Description": "DzGx9MJ",
        "As Of Date": "01/30/2010",
        "Data Source Code": "Options",
        "Dimension Value Closed Flag": "N"
    },
    {
        "Seniority Code": "5OrnCxH",
        "Standard Seniority Description": "FT89JKe",
        "As Of Date": "01/30/2010",
        "Data Source Code": "SRC3",
        "Dimension Value Closed Flag": "N"
    },
    {
        "Seniority Code": "skK3JdM",
        "Standard Seniority Description": "4dVLNpC",
        "As Of Date": "01/30/2010",
        "Data Source Code": "Loans",
        "Dimension Value Closed Flag": "N"
    },
    {
        "Seniority Code": "xPLCQGL",
        "Standard Seniority Description": "TAllyLS",
        "As Of Date": "01/30/2010",
        "Data Source Code": "ERP-FAH",
        "Dimension Value Closed Flag": "N"
    },
    {
        "Seniority Code": "2mhkpWj",
        "Standard Seniority Description": "ZPNgYKb",
        "As Of Date": "01/30/2010",
        "Data Source Code": "O6xTT8y",
        "Dimension Value Closed Flag": "N"
    },
    {
        "Seniority Code": "s5Vg4pA",
        "Standard Seniority Description": "rodrzVN",
        "As Of Date": "01/30/2010",
        "Data Source Code": "SRC5",
        "Dimension Value Closed Flag": "N"
    },
    {
        "Seniority Code": "rg7ezGD",
        "Standard Seniority Description": "187ibcb",
        "As Of Date": "01/30/2010",
        "Data Source Code": "Cards",
        "Dimension Value Closed Flag": "N"
    },
    {
        "Seniority Code": "8iKsQEa",
        "Standard Seniority Description": "IXNcvSI",
        "As Of Date": "01/30/2010",
        "Data Source Code": "LC",
        "Dimension Value Closed Flag": "N"
    },
    {
        "Seniority Code": "Yi3G3rg",
        "Standard Seniority Description": "v2pfLGC",
        "As Of Date": "01/30/2010",
        "Data Source Code": "LC",
        "Dimension Value Closed Flag": "N"
    },
    {
        "Seniority Code": "ooJURoc",
        "Standard Seniority Description": "IRqPaN6",
        "As Of Date": "01/30/2010",
        "Data Source Code": "SRC1",
        "Dimension Value Closed Flag": "N"
    },
    {
        "Seniority Code": "OTH",
        "Standard Seniority Description": "Others",
        "As Of Date": "10/30/2024",
        "Data Source Code": "",
        "Dimension Value Closed Flag": ""
    },
    {
        "Seniority Code": "MSG",
        "Standard Seniority Description": "Missing",
        "As Of Date": "10/30/2024",
        "Data Source Code": "",
        "Dimension Value Closed Flag": ""
    }
]