[
    {
        "As Of Date": "01/30/2010",
        "Forecast Scenario Name": "Ex3msW0",
        "Forecast Scenario Weightage": "560",
        "Forecast Scenario Code": "ScTaKb0",
        "Data Source Code": "Loans"
    },
    {
        "As Of Date": "01/30/2010",
        "Forecast Scenario Name": "fUvZn0x",
        "Forecast Scenario Weightage": "360",
        "Forecast Scenario Code": "d6jSGLq",
        "Data Source Code": "SRC5"
    },
    {
        "As Of Date": "01/30/2010",
        "Forecast Scenario Name": "NE1NKhb",
        "Forecast Scenario Weightage": "940",
        "Forecast Scenario Code": "yd5zr0b",
        "Data Source Code": "Cards"
    },
    {
        "As Of Date": "01/30/2010",
        "Forecast Scenario Name": "JK70nVy",
        "Forecast Scenario Weightage": "421",
        "Forecast Scenario Code": "DQtHQdQ",
        "Data Source Code": "LC"
    },
    {
        "As Of Date": "01/30/2010",
        "Forecast Scenario Name": "aAox2xA",
        "Forecast Scenario Weightage": "154",
        "Forecast Scenario Code": "A0Y88bR",
        "Data Source Code": "SRC3"
    },
    {
        "As Of Date": "01/30/2010",
        "Forecast Scenario Name": "4r1Ivgm",
        "Forecast Scenario Weightage": "751",
        "Forecast Scenario Code": "ALiy9Yu",
        "Data Source Code": "Options"
    },
    {
        "As Of Date": "01/30/2010",
        "Forecast Scenario Name": "xK1nHmE",
        "Forecast Scenario Weightage": "957",
        "Forecast Scenario Code": "yVBKRNh",
        "Data Source Code": "LC"
    },
    {
        "As Of Date": "01/30/2010",
        "Forecast Scenario Name": "L0PfeCR",
        "Forecast Scenario Weightage": "775",
        "Forecast Scenario Code": "O0KEKyp",
        "Data Source Code": "XCxKOaO"
    },
    {
        "As Of Date": "01/30/2010",
        "Forecast Scenario Name": "Bbo4n9e",
        "Forecast Scenario Weightage": "113",
        "Forecast Scenario Code": "AXtyLAE",
        "Data Source Code": "ERP-FAH"
    },
    {
        "As Of Date": "01/30/2010",
        "Forecast Scenario Name": "yendW8m",
        "Forecast Scenario Weightage": "788",
        "Forecast Scenario Code": "U8X1DjZ",
        "Data Source Code": "SRC1"
    },
    {
        "As Of Date": "10/30/2024",
        "Forecast Scenario Name": "Others",
        "Forecast Scenario Weightage": "",
        "Forecast Scenario Code": "OTH",
        "Data Source Code": ""
    },
    {
        "As Of Date": "10/30/2024",
        "Forecast Scenario Name": "Missing",
        "Forecast Scenario Weightage": "",
        "Forecast Scenario Code": "MSG",
        "Data Source Code": ""
    }
]