[
    {
        "As Of Date": "10/30/2024",
        "Securitization Status Code": "OTH",
        "Securitization Status Description": "Others",
        "Data Source Code": "",
        "Dimension Value Closed Flag": ""
    },
    {
        "As Of Date": "10/30/2024",
        "Securitization Status Code": "MSG",
        "Securitization Status Description": "Missing",
        "Data Source Code": "",
        "Dimension Value Closed Flag": ""
    },
    {
        "As Of Date": "01/30/2010",
        "Securitization Status Code": "s6BJ1Ps",
        "Securitization Status Description": "RIfh5bf",
        "Data Source Code": "Loans",
        "Dimension Value Closed Flag": "N"
    },
    {
        "As Of Date": "01/30/2010",
        "Securitization Status Code": "YyFpt3H",
        "Securitization Status Description": "kgSLK5J",
        "Data Source Code": "SRC5",
        "Dimension Value Closed Flag": "N"
    },
    {
        "As Of Date": "01/30/2010",
        "Securitization Status Code": "b7t1r68",
        "Securitization Status Description": "2ooZuQ3",
        "Data Source Code": "gMITHnR",
        "Dimension Value Closed Flag": "N"
    },
    {
        "As Of Date": "01/30/2010",
        "Securitization Status Code": "yrlGiMM",
        "Securitization Status Description": "YrWL3GQ",
        "Data Source Code": "SRC3",
        "Dimension Value Closed Flag": "N"
    },
    {
        "As Of Date": "01/30/2010",
        "Securitization Status Code": "dSeBID6",
        "Securitization Status Description": "1KtoQ1v",
        "Data Source Code": "SRC1",
        "Dimension Value Closed Flag": "N"
    },
    {
        "As Of Date": "01/30/2010",
        "Securitization Status Code": "5dC09Ep",
        "Securitization Status Description": "4zPOCXh",
        "Data Source Code": "Options",
        "Dimension Value Closed Flag": "N"
    },
    {
        "As Of Date": "01/30/2010",
        "Securitization Status Code": "fStec8M",
        "Securitization Status Description": "Gy49BTK",
        "Data Source Code": "LC",
        "Dimension Value Closed Flag": "N"
    },
    {
        "As Of Date": "01/30/2010",
        "Securitization Status Code": "d0pcTS4",
        "Securitization Status Description": "qoqGCYp",
        "Data Source Code": "LC",
        "Dimension Value Closed Flag": "N"
    },
    {
        "As Of Date": "01/30/2010",
        "Securitization Status Code": "qqau3LO",
        "Securitization Status Description": "0OK58Nc",
        "Data Source Code": "ERP-FAH",
        "Dimension Value Closed Flag": "N"
    },
    {
        "As Of Date": "01/30/2010",
        "Securitization Status Code": "PoSQx2u",
        "Securitization Status Description": "P3pektA",
        "Data Source Code": "Cards",
        "Dimension Value Closed Flag": "N"
    }
]