[
    {
        "As Of Date": "10/30/2024",
        "Underlying Asset Pool Type": "OTH",
        "Underlying Asset Pool Type Description": "Others",
        "Underlying Asset Pool Group Code": "OTH",
        "Underlying Asset Pool Group Description": "Others"
    },
    {
        "As Of Date": "10/30/2024",
        "Underlying Asset Pool Type": "MSG",
        "Underlying Asset Pool Type Description": "Missing",
        "Underlying Asset Pool Group Code": "MSG",
        "Underlying Asset Pool Group Description": "Missing"
    },
    {
        "As Of Date": "10/26/2024",
        "Underlying Asset Pool Type": "OTHCONLON",
        "Underlying Asset Pool Type Description": "Other consumer loans",
        "Underlying Asset Pool Group Code": "GRP",
        "Underlying Asset Pool Group Description": ""
    },
    {
        "As Of Date": "10/26/2024",
        "Underlying Asset Pool Type": "AUTOLON",
        "Underlying Asset Pool Type Description": "Automobile Loans",
        "Underlying Asset Pool Group Code": "GRP",
        "Underlying Asset Pool Group Description": ""
    },
    {
        "As Of Date": "10/26/2024",
        "Underlying Asset Pool Type": "MUNBON",
        "Underlying Asset Pool Type Description": "Municipal Bond",
        "Underlying Asset Pool Group Code": "GRP",
        "Underlying Asset Pool Group Description": ""
    },
    {
        "As Of Date": "10/26/2024",
        "Underlying Asset Pool Type": "COMLEAS",
        "Underlying Asset Pool Type Description": "Commercial Leases",
        "Underlying Asset Pool Group Code": "GRP",
        "Underlying Asset Pool Group Description": ""
    },
    {
        "As Of Date": "10/26/2024",
        "Underlying Asset Pool Type": "1-4FAMCEFLRESMORT",
        "Underlying Asset Pool Type Description": "1-4 Family Closed End First Lien Residential Mortgages",
        "Underlying Asset Pool Group Code": "GRP",
        "Underlying Asset Pool Group Description": ""
    },
    {
        "As Of Date": "10/26/2024",
        "Underlying Asset Pool Type": "STBON",
        "Underlying Asset Pool Type Description": "Stock/Bond Blend",
        "Underlying Asset Pool Group Code": "GRP",
        "Underlying Asset Pool Group Description": ""
    },
    {
        "As Of Date": "10/26/2024",
        "Underlying Asset Pool Type": "HELOC",
        "Underlying Asset Pool Type Description": "Home equity lines",
        "Underlying Asset Pool Group Code": "GRP",
        "Underlying Asset Pool Group Description": ""
    },
    {
        "As Of Date": "10/26/2024",
        "Underlying Asset Pool Type": "COMANDINDLON",
        "Underlying Asset Pool Type Description": "Commercial and Industrial Loans",
        "Underlying Asset Pool Group Code": "GRP",
        "Underlying Asset Pool Group Description": ""
    },
    {
        "As Of Date": "10/26/2024",
        "Underlying Asset Pool Type": "AUTOLEAS",
        "Underlying Asset Pool Type Description": "Automobile Lease",
        "Underlying Asset Pool Group Code": "GRP",
        "Underlying Asset Pool Group Description": ""
    },
    {
        "As Of Date": "10/26/2024",
        "Underlying Asset Pool Type": "OTHCOLREFASSETS",
        "Underlying Asset Pool Type Description": "Other collateral or reference assets",
        "Underlying Asset Pool Group Code": "GRP",
        "Underlying Asset Pool Group Description": ""
    },
    {
        "As Of Date": "10/26/2024",
        "Underlying Asset Pool Type": "GLOEQU",
        "Underlying Asset Pool Type Description": "Global equity",
        "Underlying Asset Pool Group Code": "GRP",
        "Underlying Asset Pool Group Description": ""
    },
    {
        "As Of Date": "10/26/2024",
        "Underlying Asset Pool Type": "1-4FAMMBSGOV",
        "Underlying Asset Pool Type Description": "1-4 Family Residential MBS issued or guaranteed by U.S. Government-Sponsored Enterprises (GSEs)",
        "Underlying Asset Pool Group Code": "GRP",
        "Underlying Asset Pool Group Description": ""
    },
    {
        "As Of Date": "10/26/2024",
        "Underlying Asset Pool Type": "TPSFIN",
        "Underlying Asset Pool Type Description": "Trust preferred securities issued by financial institutions",
        "Underlying Asset Pool Group Code": "GRP",
        "Underlying Asset Pool Group Description": ""
    },
    {
        "As Of Date": "10/26/2024",
        "Underlying Asset Pool Type": "CORPSIMLOANS",
        "Underlying Asset Pool Type Description": "Corporate and Similar Loans",
        "Underlying Asset Pool Group Code": "GRP",
        "Underlying Asset Pool Group Description": ""
    },
    {
        "As Of Date": "10/26/2024",
        "Underlying Asset Pool Type": "TAXBON",
        "Underlying Asset Pool Type Description": "Taxable Bond",
        "Underlying Asset Pool Group Code": "GRP",
        "Underlying Asset Pool Group Description": ""
    },
    {
        "As Of Date": "10/26/2024",
        "Underlying Asset Pool Type": "1-4FAMRESMBSNONGSE",
        "Underlying Asset Pool Type Description": "1-4 Family Residential MBS not issued or guaranteed by GSEs",
        "Underlying Asset Pool Group Code": "GRP",
        "Underlying Asset Pool Group Description": ""
    },
    {
        "As Of Date": "10/26/2024",
        "Underlying Asset Pool Type": "CRECARREC",
        "Underlying Asset Pool Type Description": "Credit Card Receivables",
        "Underlying Asset Pool Group Code": "GRP",
        "Underlying Asset Pool Group Description": ""
    },
    {
        "As Of Date": "10/26/2024",
        "Underlying Asset Pool Type": "PERSLOAN",
        "Underlying Asset Pool Type Description": "Personal Loans",
        "Underlying Asset Pool Group Code": "GRP",
        "Underlying Asset Pool Group Description": ""
    },
    {
        "As Of Date": "10/26/2024",
        "Underlying Asset Pool Type": "OTHRESMORT",
        "Underlying Asset Pool Type Description": "Other Residential Mortgages",
        "Underlying Asset Pool Group Code": "GRP",
        "Underlying Asset Pool Group Description": ""
    },
    {
        "As Of Date": "10/26/2024",
        "Underlying Asset Pool Type": "OTHPRESEC",
        "Underlying Asset Pool Type Description": "Other Preferred Securities",
        "Underlying Asset Pool Group Code": "GRP",
        "Underlying Asset Pool Group Description": ""
    },
    {
        "As Of Date": "10/26/2024",
        "Underlying Asset Pool Type": "1-4FAMCLOSFIRLIEN",
        "Underlying Asset Pool Type Description": "Deprecated Closed-end first lien 1-4 Family Residential Mortgages",
        "Underlying Asset Pool Group Code": "GRP",
        "Underlying Asset Pool Group Description": ""
    },
    {
        "As Of Date": "10/26/2024",
        "Underlying Asset Pool Type": "MONMAR",
        "Underlying Asset Pool Type Description": "Money market",
        "Underlying Asset Pool Group Code": "GRP",
        "Underlying Asset Pool Group Description": ""
    },
    {
        "As Of Date": "10/26/2024",
        "Underlying Asset Pool Type": "1-4FAMRESMORT",
        "Underlying Asset Pool Type Description": "Deprecated 1-4 Family Residential Mortgage Loans",
        "Underlying Asset Pool Group Code": "GRP",
        "Underlying Asset Pool Group Description": ""
    },
    {
        "As Of Date": "10/26/2024",
        "Underlying Asset Pool Type": "TRESEC",
        "Underlying Asset Pool Type Description": "Treasury Securities",
        "Underlying Asset Pool Group Code": "GRP",
        "Underlying Asset Pool Group Description": ""
    },
    {
        "As Of Date": "10/26/2024",
        "Underlying Asset Pool Type": "STUFINPROD",
        "Underlying Asset Pool Type Description": "Diversified (mixed) pools of structured financial products",
        "Underlying Asset Pool Group Code": "GRP",
        "Underlying Asset Pool Group Description": ""
    },
    {
        "As Of Date": "10/26/2024",
        "Underlying Asset Pool Type": "PERCREFAC",
        "Underlying Asset Pool Type Description": "Personal Credit Facilities",
        "Underlying Asset Pool Group Code": "GRP",
        "Underlying Asset Pool Group Description": ""
    },
    {
        "As Of Date": "10/26/2024",
        "Underlying Asset Pool Type": "MULTIFAMRESMORT",
        "Underlying Asset Pool Type Description": "Multifamily Residential Mortgages",
        "Underlying Asset Pool Group Code": "GRP",
        "Underlying Asset Pool Group Description": ""
    },
    {
        "As Of Date": "10/26/2024",
        "Underlying Asset Pool Type": "MBS",
        "Underlying Asset Pool Type Description": "Mortgage Backed Security",
        "Underlying Asset Pool Group Code": "GRP",
        "Underlying Asset Pool Group Description": ""
    },
    {
        "As Of Date": "10/26/2024",
        "Underlying Asset Pool Type": "COMCREFAC",
        "Underlying Asset Pool Type Description": "Commercial Credit Facilities",
        "Underlying Asset Pool Group Code": "GRP",
        "Underlying Asset Pool Group Description": ""
    },
    {
        "As Of Date": "10/26/2024",
        "Underlying Asset Pool Type": "DOMEQU",
        "Underlying Asset Pool Type Description": "Domestic equity",
        "Underlying Asset Pool Group Code": "GRP",
        "Underlying Asset Pool Group Description": ""
    },
    {
        "As Of Date": "10/26/2024",
        "Underlying Asset Pool Type": "SINGLENAME",
        "Underlying Asset Pool Type Description": "Single Entity Exposure",
        "Underlying Asset Pool Group Code": "GRP",
        "Underlying Asset Pool Group Description": ""
    },
    {
        "As Of Date": "10/26/2024",
        "Underlying Asset Pool Type": "STULOAN",
        "Underlying Asset Pool Type Description": "Student Loans",
        "Underlying Asset Pool Group Code": "GRP",
        "Underlying Asset Pool Group Description": ""
    },
    {
        "As Of Date": "10/26/2024",
        "Underlying Asset Pool Type": "TPSREESINVTS",
        "Underlying Asset Pool Type Description": "Trust preferred securities issued by real estate investment trusts",
        "Underlying Asset Pool Group Code": "GRP",
        "Underlying Asset Pool Group Description": ""
    },
    {
        "As Of Date": "10/26/2024",
        "Underlying Asset Pool Type": "1-4FAMREVOPENRESMORT",
        "Underlying Asset Pool Type Description": "1-4 Family Revolving Open End Residential Mortgages",
        "Underlying Asset Pool Group Code": "GRP",
        "Underlying Asset Pool Group Description": ""
    },
    {
        "As Of Date": "10/26/2024",
        "Underlying Asset Pool Type": "1-4FAMCEJLRESMORT",
        "Underlying Asset Pool Type Description": "1-4 Family Closed End Junior Lien Residential Mortgages",
        "Underlying Asset Pool Group Code": "GRP",
        "Underlying Asset Pool Group Description": ""
    }
]