[
    {
        "As Of Date": "01/30/2010",
        "Vehicle Body Type": "cWhs0sG",
        "Vehicle Body Type Description": "2nrejak",
        "Data Source Code": "LC",
        "Dimension Value Closed Flag": "N"
    },
    {
        "As Of Date": "01/30/2010",
        "Vehicle Body Type": "qnte1F5",
        "Vehicle Body Type Description": "NadAVTm",
        "Data Source Code": "LC",
        "Dimension Value Closed Flag": "N"
    },
    {
        "As Of Date": "01/30/2010",
        "Vehicle Body Type": "s6TyF2z",
        "Vehicle Body Type Description": "i8of03E",
        "Data Source Code": "ERP-FAH",
        "Dimension Value Closed Flag": "N"
    },
    {
        "As Of Date": "01/30/2010",
        "Vehicle Body Type": "lfLIfJ5",
        "Vehicle Body Type Description": "fqdrGq1",
        "Data Source Code": "SRC3",
        "Dimension Value Closed Flag": "N"
    },
    {
        "As Of Date": "01/30/2010",
        "Vehicle Body Type": "FLF37sS",
        "Vehicle Body Type Description": "WrYvURo",
        "Data Source Code": "Loans",
        "Dimension Value Closed Flag": "N"
    },
    {
        "As Of Date": "01/30/2010",
        "Vehicle Body Type": "ii2jCLX",
        "Vehicle Body Type Description": "J7mr7Qo",
        "Data Source Code": "SRC5",
        "Dimension Value Closed Flag": "N"
    },
    {
        "As Of Date": "01/30/2010",
        "Vehicle Body Type": "D3dydLQ",
        "Vehicle Body Type Description": "5GcrGKs",
        "Data Source Code": "Cards",
        "Dimension Value Closed Flag": "N"
    },
    {
        "As Of Date": "01/30/2010",
        "Vehicle Body Type": "PZ0vaSr",
        "Vehicle Body Type Description": "VTjWRv5",
        "Data Source Code": "Options",
        "Dimension Value Closed Flag": "N"
    },
    {
        "As Of Date": "01/30/2010",
        "Vehicle Body Type": "b1k4FMl",
        "Vehicle Body Type Description": "msJmQFS",
        "Data Source Code": "SRC1",
        "Dimension Value Closed Flag": "N"
    },
    {
        "As Of Date": "01/30/2010",
        "Vehicle Body Type": "TT4UJ4T",
        "Vehicle Body Type Description": "hJOOCpe",
        "Data Source Code": "7ivVRCV",
        "Dimension Value Closed Flag": "N"
    },
    {
        "As Of Date": "10/30/2024",
        "Vehicle Body Type": "OTH",
        "Vehicle Body Type Description": "Others",
        "Data Source Code": "",
        "Dimension Value Closed Flag": ""
    },
    {
        "As Of Date": "10/30/2024",
        "Vehicle Body Type": "MSG",
        "Vehicle Body Type Description": "Missing",
        "Data Source Code": "",
        "Dimension Value Closed Flag": ""
    }
]