[
    {
        "As Of Date": "01/30/2010",
        "Watch List Identifier": "iG916CP",
        "Watch List Name": "A09Adnd",
        "Watch List Description": "qqREA6c",
        "Watch List Type": "cD5R3Zo"
    },
    {
        "As Of Date": "01/30/2010",
        "Watch List Identifier": "DxZcQp0",
        "Watch List Name": "gpc9unG",
        "Watch List Description": "69CgrJ2",
        "Watch List Type": "b6zlMQQ"
    },
    {
        "As Of Date": "01/30/2010",
        "Watch List Identifier": "WFFJpzA",
        "Watch List Name": "7asCsfE",
        "Watch List Description": "MCxzU3j",
        "Watch List Type": "n3tJH9P"
    },
    {
        "As Of Date": "01/30/2010",
        "Watch List Identifier": "hkSMVfS",
        "Watch List Name": "i8PTItH",
        "Watch List Description": "TWf2pKz",
        "Watch List Type": "GrLjzxu"
    },
    {
        "As Of Date": "01/30/2010",
        "Watch List Identifier": "S26YR7M",
        "Watch List Name": "c7rozuc",
        "Watch List Description": "iqcz1Oi",
        "Watch List Type": "abkHPQE"
    },
    {
        "As Of Date": "01/30/2010",
        "Watch List Identifier": "ANSV6RS",
        "Watch List Name": "xg1Rqv8",
        "Watch List Description": "BUfxTHz",
        "Watch List Type": "2yMFmJS"
    },
    {
        "As Of Date": "01/30/2010",
        "Watch List Identifier": "b9HOC7s",
        "Watch List Name": "1Yyl1Ac",
        "Watch List Description": "V5pzq2y",
        "Watch List Type": "mOdsEfK"
    },
    {
        "As Of Date": "01/30/2010",
        "Watch List Identifier": "nLH3eMD",
        "Watch List Name": "GNroYN0",
        "Watch List Description": "YliupZC",
        "Watch List Type": "bo4BtRJ"
    },
    {
        "As Of Date": "01/30/2010",
        "Watch List Identifier": "ZmJ5H7u",
        "Watch List Name": "I3oK5HB",
        "Watch List Description": "bObXVJE",
        "Watch List Type": "Bgok6US"
    },
    {
        "As Of Date": "01/30/2010",
        "Watch List Identifier": "eWiASqf",
        "Watch List Name": "OJFSiyy",
        "Watch List Description": "4Zvs8hv",
        "Watch List Type": "urbPgJv"
    },
    {
        "As Of Date": "10/30/2024",
        "Watch List Identifier": "OTH",
        "Watch List Name": "Others",
        "Watch List Description": "Others",
        "Watch List Type": "OTH"
    },
    {
        "As Of Date": "10/30/2024",
        "Watch List Identifier": "MSG",
        "Watch List Name": "Missing",
        "Watch List Description": "Missing",
        "Watch List Type": "MSG"
    }
]